dlrm-0.2.16.dist-info/licenses/LICENSE
rm/__init__.py
rm/tool.py
rm/wrapper_tool.py
rm/db/db.py
rm/db/db_tree.py
rm/db/factory.py
rm/db/record.py
rm/db/view.py
rm/dirdb/__init__.py
rm/dirdb/dirdb.py
rm/dirdb/factory.py
rm/dirdb/metadata.py
rm/dirtree/__init__.py
rm/dirtree/dir_name_id_manager.py
rm/dirtree/dir_tree.py
rm/dirtree/factory.py
rm/dirtree/file_name_id_manager.py
rm/dirtree/test.py
rm/hook/hook.py
rm/memo/__init__.py
rm/memo/factory.py
rm/memo/file_io.py
rm/memo/memo.py
rm/memo/property_memo.py
rm/property_manager/factory.py
rm/property_manager/property_manager.py
rm/resource_db/__init__.py
rm/resource_db/base_model.py
rm/resource_db/db.py
rm/resource_db/factory.py
rm/resource_db/record.py
rm/resource_db/view.py
rm/tree/hooking_tree.py
rm/tree/path_tree.py
rm/tree/tree.py
dlrm-0.2.16.dist-info/METADATA
dlrm-0.2.16.dist-info/WHEEL
dlrm-0.2.16.dist-info/top_level.txt
dlrm-0.2.16.dist-info/RECORD
