Metadata-Version: 2.4
Name: dlrm
Version: 0.2.16
Summary: resource management with file system in deep learning research
Author-email: Myounghun Han <hoonisone@gmail.com>
License: MIT
Requires-Python: >=3.8
License-File: LICENSE
Provides-Extra: dev
Requires-Dist: pytest; extra == "dev"
Requires-Dist: black; extra == "dev"
Dynamic: license-file
